recsys_slates_dataset/__init__.py
recsys_slates_dataset/_modidx.py
recsys_slates_dataset/_nbdev.py
recsys_slates_dataset/core.py
recsys_slates_dataset/data_helper.py
recsys_slates_dataset/dataset_torch.py
recsys_slates_dataset/lightning_helper.py
recsys_slates_dataset-1.0.3.dist-info/LICENSE
recsys_slates_dataset-1.0.3.dist-info/METADATA
recsys_slates_dataset-1.0.3.dist-info/WHEEL
recsys_slates_dataset-1.0.3.dist-info/entry_points.txt
recsys_slates_dataset-1.0.3.dist-info/top_level.txt
recsys_slates_dataset-1.0.3.dist-info/RECORD
