Metadata-Version: 2.1
Name: recsys-slates-dataset
Version: 1.0.3
Summary: Recommender Systems Dataset from FINN.no containing the presented items and whether and what the user clicked on.
Home-page: https://github.com/finn-no/recsys_slates_dataset/tree/main/
Author: simen eide
Author-email: simeneide@gmail.com
License: tbd
Keywords: recommender systems,dataset,slates,recsys
Platform: UNKNOWN
Classifier: Development Status :: 3 - Alpha
Classifier: Intended Audience :: Developers
Classifier: Natural Language :: English
Classifier: Programming Language :: Python :: 3.6
Classifier: Programming Language :: Python :: 3.7
Classifier: Programming Language :: Python :: 3.8
Classifier: Programming Language :: Python :: 3.9
Classifier: Programming Language :: Python :: 3.10
Requires-Python: >=3.6
Requires-Dist: requests (>=2.25.1)
Requires-Dist: numpy (>=1.19.5)
Requires-Dist: pandas (>=1.0.5)
Requires-Dist: torch (>=1.9.0)
Requires-Dist: PyYAML (==5.4.1)
Requires-Dist: gdown (==4.5.1)
Requires-Dist: pytorch-lightning (>=1.4.1)
Provides-Extra: dev
